polymcsim/__init__.py
polymcsim/core.py
polymcsim/schemas.py
polymcsim/simulation.py
polymcsim/utils.py
polymcsim/visualization.py
polymcsim/polymer_generation/__init__.py
polymcsim/polymer_generation/optim.py
polymcsim-0.8.0.dist-info/METADATA
polymcsim-0.8.0.dist-info/WHEEL
polymcsim-0.8.0.dist-info/top_level.txt
polymcsim-0.8.0.dist-info/RECORD
