Metadata-Version: 2.4
Name: polymcsim
Version: 0.8.0
Summary: A high-performance Python library for Monte Carlo polymer graph generation
Author-email: Your Name <your.email@example.com>
Requires-Python: >=3.11
Requires-Dist: numpy>=1.24.0
Requires-Dist: scipy>=1.10.0
Requires-Dist: numba>=0.57.0
Requires-Dist: pydantic>=2.0.0
Requires-Dist: networkx>=3.0
Requires-Dist: matplotlib>=3.8.0
Requires-Dist: tqdm
Requires-Dist: pandas>=2.0.0
Requires-Dist: optuna>=4.4.0
Provides-Extra: dev
Requires-Dist: pytest>=8.4.1; extra == "dev"
Requires-Dist: pytest-cov>=4.0.0; extra == "dev"
Requires-Dist: pytest-timeout>=2.1.0; extra == "dev"
Requires-Dist: mypy>=1.0.0; extra == "dev"
Requires-Dist: pre-commit>=3.0.0; extra == "dev"
Requires-Dist: pytest-benchmark>=5.1.0; extra == "dev"
Requires-Dist: commitizen>=4.8.3; extra == "dev"
Provides-Extra: doc
Requires-Dist: mkdocs>=1.6.1; extra == "doc"
Requires-Dist: mkdocs-material>=9.6.14; extra == "doc"
Requires-Dist: mkdocs-gen-files>=0.5.0; extra == "doc"
Requires-Dist: mkdocstrings[python]>=0.29.1; extra == "doc"
